Metadata-Version: 2.1
Name: chipi
Version: 0.0.1
Summary: buffer management tool for Python
Home-page: https://github.com/remokasu/chipi
Author: remokasu
License: MIT License
License-File: LICENSE
